intinfo.py
ioctl_requests.c
setup.py
intinfo.egg-info/PKG-INFO
intinfo.egg-info/SOURCES.txt
intinfo.egg-info/dependency_links.txt
intinfo.egg-info/top_level.txt