Metadata-Version: 1.0
Name: intinfo
Version: 0.1
Summary: Its hard to get network interface information in python in a portable manner. This should help, at least in *nix environments.
Home-page: http://github.com/mastahyeti/intinfo
Author: Ben Toews (mastahyeti)
Author-email: mastahyeti@gmail.com
License: GPL v3
Platform: UNKNOWN
